tvmux/__init__.py
tvmux/api_client.py
tvmux/config.py
tvmux/connection.py
tvmux/repair.py
tvmux/utils.py
tvmux/cli/__init__.py
tvmux/cli/api_cli.py
tvmux/cli/config.py
tvmux/cli/main.py
tvmux/cli/record.py
tvmux/cli/server.py
tvmux/cli/tui.py
tvmux/models/__init__.py
tvmux/models/pane.py
tvmux/models/position.py
tvmux/models/recording.py
tvmux/models/remote.py
tvmux/models/session.py
tvmux/models/window.py
tvmux/proc/__init__.py
tvmux/proc/bg.py
tvmux/server/__init__.py
tvmux/server/main.py
tvmux/server/state.py
tvmux/server/window_monitor.py
tvmux/server/routers/__init__.py
tvmux/server/routers/callbacks.py
tvmux/server/routers/hook.py
tvmux/server/routers/panes.py
tvmux/server/routers/recording.py
tvmux/server/routers/session.py
tvmux/server/routers/window.py
tvmux/tui/__init__.py
tvmux/tui/app.py
tvmux-0.6.1.dist-info/entry_points.txt
tvmux-0.6.1.dist-info/licenses/LICENSE.md
tvmux-0.6.1.dist-info/WHEEL
tvmux-0.6.1.dist-info/METADATA
tvmux-0.6.1.dist-info/RECORD
