Metadata-Version: 2.4
Name: tvmux
Version: 0.6.1
Summary: terminal multiplexer recorder
Author-email: Gareth Davidson <gaz@bitplane.net>
Requires-Python: >=3.11
License-File: LICENSE.md
Requires-Dist: click>=8.2
Requires-Dist: pydantic>=2.11
Requires-Dist: fastapi>=0.109
Requires-Dist: uvicorn>=0.27
Requires-Dist: httpx>=0.25
Requires-Dist: psutil>=5.9
Requires-Dist: asciinema>=2.4
Requires-Dist: requests>=2.0
Requires-Dist: tomli>=1.2.0
Requires-Dist: tomli-w>=1.0.0
Requires-Dist: textual>=5.2.0
Requires-Dist: textual-asciinema>=0.0.3
Requires-Dist: pre-commit ; extra == "dev"
Requires-Dist: pytest ; extra == "dev"
Requires-Dist: coverage ; extra == "dev"
Requires-Dist: pytest-cov ; extra == "dev"
Requires-Dist: build ; extra == "dev"
Requires-Dist: twine ; extra == "dev"
Requires-Dist: ruff ; extra == "dev"
Requires-Dist: pydoc-markdown ; extra == "dev"
Provides-Extra: dev
